[
    {
        "category": "内閣府",
        "title": "重要なお知らせ、国民参加型の行事等の情報については「新着情報」のRSSフィードにて提供しています。",
        "link": "http://www.cao.go.jp/rss/index.html"
    },
    {
        "category": "財務省",
        "title": "国債の償還予定額（令和7年9月分）",
        "link": "https://www.mof.go.jp/insideLink/20250828115900.html"
    },
    {
        "category": "財務省",
        "title": "財政投融資分科会（令和7年6月25日開催）議事録",
        "link": "https://www.mof.go.jp/about_mof/councils/fiscal_system_council/sub-of_filp/proceedings/proceedings/zaitoa20250625.html"
    },
    {
        "category": "財務省",
        "title": "国債金利情報(令和7年8月28日)",
        "link": "https://www.mof.go.jp/jgbs/reference/interest_rate/jgbcm.csv"
    },
    {
        "category": "経済産業省",
        "title": "経済産業省生産動態統計速報（2025年7月分）",
        "link": "https://www.meti.go.jp/statistics/tyo/seidou/result/ichiran/08_seidou.html?pk_campaign=rss_statistics"
    },
    {
        "category": "経済産業省",
        "title": "鉱工業出荷内訳表・総供給表(2025年7月分)",
        "link": "https://www.meti.go.jp/statistics/tyo/utiwake/b2020_result-2.html?pk_campaign=rss_statistics"
    },
    {
        "category": "経済産業省",
        "title": "製造工業生産予測指数（2025年8月調査）",
        "link": "https://www.meti.go.jp/statistics/tyo/yosoku/result-1.html?pk_campaign=rss_statistics"
    },
    {
        "category": "経済産業省",
        "title": "鉱工業生産・出荷・在庫指数速報（2025年7月分）",
        "link": "https://www.meti.go.jp/statistics/tyo/iip/result-1.html?pk_campaign=rss_statistics"
    },
    {
        "category": "経済産業省",
        "title": "商業動態統計速報（2025年7月分）",
        "link": "https://www.meti.go.jp/statistics/tyo/syoudou/result/sokuho_1.html?pk_campaign=rss_statistics"
    },
    {
        "category": "財務省",
        "title": "新型窓口販売方式による2年利付国債（第476回）の発行条件等",
        "link": "https://www.mof.go.jp/jgbs/individual/kojinmuke/houdouhappyou/shinmado20250829.htm"
    },
    {
        "category": "厚生労働省",
        "title": "一般職業紹介状況(令和7年7月分)について",
        "link": "https://www.mhlw.go.jp/stf/newpage_62187.html"
    },
    {
        "category": "総務省",
        "title": "労働力調査（基本集計）2025年（令和7年）7月分",
        "link": "https://www.soumu.go.jp/menu_news/s-news/01toukei04_01000284.html"
    },
    {
        "category": "総務省",
        "title": "2020年基準 消費者物価指数 東京都区部 2025年(令和7年)8月分(中旬速報値)",
        "link": "https://www.soumu.go.jp/menu_news/s-news/01toukei08_01000321.html"
    },
    {
        "category": "総務省",
        "title": "デジタル変革を通じた持続可能な地域社会と強い経済基盤の実現（総務省重点施策2026）",
        "link": "https://www.soumu.go.jp/menu_news/s-news/01kanbo05_02000197.html"
    },
    {
        "category": "総務省",
        "title": "令和8年度総務省所管予算概算要求の概要等",
        "link": "https://www.soumu.go.jp/menu_news/s-news/01kanbo04_02000248.html"
    },
    {
        "category": "総務省",
        "title": "令和8年度の地方財政の課題",
        "link": "https://www.soumu.go.jp/menu_news/s-news/01zaisei02_02000402.html"
    },
    {
        "category": "財務省",
        "title": "製造たばこの小売定価の認可",
        "link": "https://www.mof.go.jp/policy/tab_salt/topics/kouriteika.html"
    },
    {
        "category": "農林水産省",
        "title": "令和8年度農林水産予算概算要求の概要について",
        "link": "https://www.maff.go.jp/j/press/kanbo/yosan/250829.html"
    },
    {
        "category": "農林水産省",
        "title": "令和8年度組織・定員要求について",
        "link": "https://www.maff.go.jp/j/press/kanbo/hisyo/250829.html"
    },
    {
        "category": "農林水産省",
        "title": "令和8年度税制改正要望について",
        "link": "https://www.maff.go.jp/j/press/keiei/tyosei/250829.html"
    },
    {
        "category": "消費者庁",
        "title": "景品表示法に基づく法的措置件数の推移及び措置事件の概要の公表(令和7年7月31日現在)",
        "link": "https://www.caa.go.jp/notice/entry/024740/"
    },
    {
        "category": "農林水産省",
        "title": "滝波農林水産副大臣の海外出張（トルコ、スロベニア）について",
        "link": "https://www.maff.go.jp/j/press/yusyutu_kokusai/chiiki/250829.html"
    },
    {
        "category": "厚生労働省",
        "title": "９月10日から９月16日は「自殺予防週間」です",
        "link": "https://www.mhlw.go.jp/stf/r7_jisatsuyoboushukan.html"
    },
    {
        "category": "財務省",
        "title": "国庫短期証券（第1328回）の入札発行",
        "link": "https://www.mof.go.jp/jgbs/auction/calendar/tbill/tbill_nyusatsu/offer20250829.htm"
    },
    {
        "category": "財務省",
        "title": "国庫短期証券（第1329回）の発行予定額等",
        "link": "https://www.mof.go.jp/jgbs/auction/calendar/tbill/tbill_auct/auct20250829.htm"
    },
    {
        "category": "厚生労働省",
        "title": "21世紀出生児縦断調査（平成22年出生児）対象者のみなさまへ",
        "link": "https://www.mhlw.go.jp/toukei/saikin/hw/judan/taishousha/sn_07.html"
    },
    {
        "category": "法務省",
        "title": "令和６年分年報公表（検察統計）及び令和６年度分年報公表（戸籍統計及び供託統計）",
        "link": "http://www.moj.go.jp/housei/toukei/toukei_ichiran_index.html"
    },
    {
        "category": "法務省",
        "title": "令和８年度概算要求",
        "link": "http://www.moj.go.jp/kaikei/bunsho/kaikei02_00150.html"
    },
    {
        "category": "消費者庁",
        "title": "令和7年度開催「国民生活センター評価等のための有識者懇談会」の会議資料を掲載しました",
        "link": "https://www.caa.go.jp/notice/entry/043358/"
    },
    {
        "category": "消費者庁",
        "title": "独立行政法人国民生活センター令和6年度の業務実績に対する主務大臣の評価を公表しました",
        "link": "https://www.caa.go.jp/notice/entry/043401/"
    },
    {
        "category": "厚生労働省",
        "title": "世界メンタルヘルスデー JAPAN 2025 特設サイト",
        "link": "https://www.mhlw.go.jp/kokoro/mental_health_day/"
    },
    {
        "category": "首相官邸",
        "title": "閣議の概要について",
        "link": "https://www.kantei.go.jp/jp/tyoukanpress/202508/29_a.html"
    },
    {
        "category": "文部科学省",
        "title": "令和8年度文部科学省　概算要求等の発表資料一覧",
        "link": "https://www.mext.go.jp/a_menu/yosan/r01/1420668_00003.html"
    },
    {
        "category": "国土交通省",
        "title": "ＡＮＡウイングス株式会社に対する厳重注意について",
        "link": "http://www.mlit.go.jp/report/press/kouku10_hh_000292.html"
    },
    {
        "category": "国土交通省",
        "title": "建築物に係る防火関係規制の見直し等について〜「建築基準法施行令の一部を改正する政令」を閣議決定〜",
        "link": "http://www.mlit.go.jp/report/press/house05_hh_001079.html"
    },
    {
        "category": "経済産業省",
        "title": "令和6年能登半島地震等「中小企業特定施設等災害復旧費補助金（なりわい再建支援事業）」の交付決定を行いました～新潟県の7者を交付決定～",
        "link": "https://www.chusho.meti.go.jp/keiei/shokibo/2025/250829nariwai.html"
    },
    {
        "category": "文部科学省",
        "title": "文部科学大臣メッセージ「～不安や悩みがあったら話してみよう～」",
        "link": "https://www.mext.go.jp/a_menu/shotou/seitoshidou/mext_00003.html"
    },
    {
        "category": "農林水産省",
        "title": "野菜の生育状況及び価格見通し（令和7年9月）について",
        "link": "https://www.maff.go.jp/j/press/nousan/engei/250829.html"
    },
    {
        "category": "農林水産省",
        "title": "民有林の無断伐採に係る調査結果（令和6年）について",
        "link": "https://www.rinya.maff.go.jp/j/press/keikaku/250829.html"
    },
    {
        "category": "厚生労働省",
        "title": "令和７年度大学における恒久定員内地域枠設置促進事業実施団体の公募について（二次募集）",
        "link": "https://www.mhlw.go.jp/stf/seisakunitsuite/bunya/0000200195_00037.html"
    },
    {
        "category": "厚生労働省",
        "title": "「令和６年外国人雇用実態調査」の結果を\n公表します",
        "link": "https://www.mhlw.go.jp/stf/newpage_61317.html"
    },
    {
        "category": "厚生労働省",
        "title": "令和７年度「地域雇用活性化推進事業」の採択地域を決定しました。",
        "link": "https://www.mhlw.go.jp/stf/newpage_61862.html"
    },
    {
        "category": "厚生労働省",
        "title": "第10回機能性表示食品等の健康被害情報への対応に関する小委員会（第１小委員会）（Web会議）を開催します。（開催案内）",
        "link": "https://www.mhlw.go.jp/stf/other-kenkou_128610_00030.html"
    },
    {
        "category": "厚生労働省",
        "title": "令和７年度「障害者雇用優良事業所等の厚生労働大臣表彰」受賞者決定",
        "link": "https://www.mhlw.go.jp/stf/newpage_62174.html"
    },
    {
        "category": "厚生労働省",
        "title": "第177回労働政策審議会安全衛生分科会（開催案内）",
        "link": "https://www.mhlw.go.jp/stf/newpage_62177.html"
    },
    {
        "category": "厚生労働省",
        "title": "医科医療費（電算処理分）の動向　～令和6年度版～",
        "link": "https://www.mhlw.go.jp/stf/seisakunitsuite/bunya/iryouhoken/database/zenpan/ika_iryou_doukou_r06.html"
    },
    {
        "category": "厚生労働省",
        "title": "危険ドラッグの成分３物質を新たに指定薬物に指定",
        "link": "https://www.mhlw.go.jp/stf/houdou/0000212707_00031.html"
    },
    {
        "category": "厚生労働省",
        "title": "令和７年度地域医療介護総合確保基金（医療分）の第１回内示について",
        "link": "https://www.mhlw.go.jp/stf/newpage_62567.html"
    },
    {
        "category": "厚生労働省",
        "title": "医療施設動態調査（令和7年6月末概数）",
        "link": "https://www.mhlw.go.jp/toukei/saikin/hw/iryosd/m25/is2505.html"
    },
    {
        "category": "厚生労働省",
        "title": "最近の医療費の動向-MEDIAS-令和6年度3月号",
        "link": "https://www.mhlw.go.jp/topics/medias/month/25/03.html"
    },
    {
        "category": "厚生労働省",
        "title": "最近の医科医療費（電算処理分）の動向　令和6年度3月号",
        "link": "https://www.mhlw.go.jp/topics/medias/ika_iryou/2025/03/"
    },
    {
        "category": "厚生労働省",
        "title": "最近の歯科医療費（電算処理分）の動向　令和6年度3月号",
        "link": "https://www.mhlw.go.jp/topics/medias/shika_iryou/2025/03/"
    },
    {
        "category": "厚生労働省",
        "title": "最近の調剤医療費（電算処理分）の動向　令和6年度3月号",
        "link": "https://karikeisai-www.mhlw.go.jp/topics/medias/c-med/2025/03/"
    },
    {
        "category": "厚生労働省",
        "title": "医療費の動向（年次版）　令和６年度",
        "link": "https://www.mhlw.go.jp/topics/medias/year/24/index.html"
    },
    {
        "category": "厚生労働省",
        "title": "歯科医療費（電算処理分）の動向　～令和6年度版～",
        "link": "https://www.mhlw.go.jp/topics/medias/year/24/shika_iryou_doukou_r06.html"
    },
    {
        "category": "厚生労働省",
        "title": "調剤医療費（電算処理分）の動向　～令和6年度版～",
        "link": "https://www.mhlw.go.jp/topics/medias/year/24/gaiyou.html"
    },
    {
        "category": "文部科学省",
        "title": "令和8年度からの私立大学等の収容定員の変更に係る学則変更予定一覧について（答申）",
        "link": "https://www.mext.go.jp/b_menu/shingi/daigaku/toushin/1422602_00009.htm"
    },
    {
        "category": "文部科学省",
        "title": "令和8年度開設予定の大学の学部等の設置届出について（令和7年4月分）",
        "link": "https://www.mext.go.jp/a_menu/koutou/ninka/1418456_00073.htm"
    },
    {
        "category": "文部科学省",
        "title": "令和8年度開設予定の大学等の設置等に係る答申について",
        "link": "https://www.mext.go.jp/b_menu/shingi/daigaku/toushin/attach/1420729_00023.htm"
    },
    {
        "category": "文部科学省",
        "title": "文部科学省大臣官房会計課非常勤職員（期間業務職員）採用のお知らせ（令和7年10月1日予定）",
        "link": "https://www.mext.go.jp/b_menu/saiyou/hijyoukin/1423086_00152.htm"
    },
    {
        "category": "文部科学省",
        "title": "大学等の設置者変更に係る答申について",
        "link": "https://www.mext.go.jp/b_menu/shingi/daigaku/toushin/attach/1421012_00006.htm"
    },
    {
        "category": "文部科学省",
        "title": "令和8年度 国立大学の入学定員（予定）について",
        "link": "https://www.mext.go.jp/a_menu/koutou/houjin/1408700_00010.html"
    },
    {
        "category": "総務省",
        "title": "令和７年度全国少年消防クラブ交流大会を開催します（令和７年８月29日）",
        "link": "https://www.fdma.go.jp/pressrelease/houdou/#068994"
    },
    {
        "category": "総務省",
        "title": "消防団の組織概要等に関する調査（令和７年度）の結果（令和７年８月29日）",
        "link": "https://www.fdma.go.jp/pressrelease/houdou/#068997"
    },
    {
        "category": "農林水産省",
        "title": "令和7年7月末現在の米穀流通の動向（集荷、販売、民間在庫）",
        "link": "https://www.maff.go.jp/j/press/nousan/kikaku/250829.html"
    },
    {
        "category": "農林水産省",
        "title": "令和7年度我が国周辺水域の水産資源に関する評価結果が公表されました（マアジ、マイワシ、ウルメイワシ、カタクチイワシ、キンメダイ、トラフグ、マダイ）",
        "link": "https://www.jfa.maff.go.jp/j/press/sigen/250829.html"
    },
    {
        "category": "厚生労働省",
        "title": "令和８年度厚生労働省所管予算概算要求関係",
        "link": "https://www.mhlw.go.jp/wp/yosan/yosan/26syokan/"
    },
    {
        "category": "文部科学省",
        "title": "令和7年度「次世代型オープンイノベーションのモデル形成事業」の採択機関の決定について",
        "link": "https://www.mext.go.jp/b_menu/boshu/detail/mext_00486.html"
    },
    {
        "category": "消費者庁",
        "title": "食べ残し持ち帰り促進ガイドラインに関する研修会開催のお知らせ",
        "link": "https://www.caa.go.jp/notice/entry/043409/"
    },
    {
        "category": "財務省",
        "title": "APG（アジア・太平洋マネー・ローンダリング対策グループ）年次総会の東京開催について（令和7年8月25日（月）～29日（金））",
        "link": "https://www.mof.go.jp/policy/international_policy/convention/fatf/250829.html"
    },
    {
        "category": "財務省",
        "title": "「令和７年度租税特別措置等に係る政策の事前評価書」を公表します",
        "link": "https://www.mof.go.jp/about_mof/policy_evaluation/mof/fy2025/evaluation2/2025sotokukouhyou.html"
    },
    {
        "category": "農林水産省",
        "title": "令和6年度日本型直接支払の実施状況について",
        "link": "https://www.maff.go.jp/j/press/nousin/nihon/250829.html"
    },
    {
        "category": "法務省",
        "title": "司法試験等のデジタル化のページを更新しました。",
        "link": "http://www.moj.go.jp/jinji/shihoushiken/jinji08_00238.html"
    },
    {
        "category": "厚生労働省",
        "title": "第34回アルコール健康障害対策関係者会議　議事録",
        "link": "https://www.mhlw.go.jp/stf/newpage_62663.html"
    },
    {
        "category": "消費者庁",
        "title": "消費生活用製品の重大製品事故:長期使用の扇風機についての注意喚起、リコール製品で火災等(高圧洗浄機(充電式))(8月29日)",
        "link": "https://www.caa.go.jp/notice/entry/043412/"
    },
    {
        "category": "経済産業省",
        "title": "令和7年台風第12号に伴う災害に関して被災中小企業・小規模事業者支援措置を行います",
        "link": "https://www.meti.go.jp/press/2025/08/20250829004/20250829004.html"
    },
    {
        "category": "厚生労働省",
        "title": "「人口動態統計速報」令和７年６月分",
        "link": "https://www.mhlw.go.jp/toukei/saikin/hw/jinkou/geppo/s2025/06.html"
    },
    {
        "category": "文部科学省",
        "title": "教育行政に係る法務相談体制の整備等に関する調査結果（令和4年度間）を掲載しました。",
        "link": "https://www.mext.go.jp/a_menu/houmusoudan/index.htm"
    },
    {
        "category": "文部科学省",
        "title": "深海・海溝域の探査・採取プラットフォームについて（提言）",
        "link": "https://www.mext.go.jp/b_menu/shingi/gijyutu/gijyutu5/reports/1422778_00007.htm"
    },
    {
        "category": "文部科学省",
        "title": "海洋・地球科学分野における質量分析技術報告書",
        "link": "https://www.mext.go.jp/b_menu/shingi/gijyutu/gijyutu5/reports/1422778_00006.htm"
    },
    {
        "category": "復興庁",
        "title": "令和８年度復興庁予算概算要求（令和７年８月29日）",
        "link": "https://www.reconstruction.go.jp/topics/main-cat8/sub-cat8-3/20250829101641.html"
    },
    {
        "category": "復興庁",
        "title": "令和８年度税制改正要望について",
        "link": "https://www.reconstruction.go.jp/topics/main-cat8/sub-cat8-3/20250828145712.html"
    },
    {
        "category": "内閣府",
        "title": "ESRI Discussion Paper No.403 「主観的金融政策ショックが消費に与える影響」",
        "link": "https://www.esri.cao.go.jp/jp/esri/archive/e_dis/2025/e_dis403.html"
    },
    {
        "category": "厚生労働省",
        "title": "労働基準関係法令違反に係る公表事案",
        "link": "https://www.mhlw.go.jp/kinkyu/151106.html"
    },
    {
        "category": "農林水産省",
        "title": "令和６年度国産農畜水産物に含まれる有機フッ素化合物（PFAS）の実態調査や試験研究の結果について",
        "link": "https://www.maff.go.jp/j/press/syouan/seisaku/250828.html"
    },
    {
        "category": "厚生労働省",
        "title": "薬剤師国家試験の施行について",
        "link": "https://www.mhlw.go.jp/kouseiroudoushou/shikaku_shiken/yakuzaishi/"
    },
    {
        "category": "厚生労働省",
        "title": "再生医療等の安全性の確保等に関する法律に基づく緊急命令について",
        "link": "https://www.mhlw.go.jp/stf/newpage_62642.html"
    },
    {
        "category": "文部科学省",
        "title": "デジタル教科書推進ワーキンググループ（第11回）の開催について",
        "link": "https://www.mext.go.jp/b_menu/shingi/chukyo/chukyo3/100/kaisai/mext_00014.html"
    },
    {
        "category": "厚生労働省",
        "title": "「薬局・薬剤師の機能強化等に関する検討会」の「これまでの議論のまとめ」を公表します",
        "link": "https://www.mhlw.go.jp/stf/newpage_62429.html"
    }
]