[
    {
        "category": "内閣府",
        "title": "重要なお知らせ、国民参加型の行事等の情報については「新着情報」のRSSフィードにて提供しています。",
        "link": "http://www.cao.go.jp/rss/index.html"
    },
    {
        "category": "財務省",
        "title": "入札、落札結果情報（物品・役務）",
        "link": "https://www.mof.go.jp/application-contact/procurement/buppinn/index.htm"
    },
    {
        "category": "財務省",
        "title": "国債金利情報(令和8年1月15日)",
        "link": "https://www.mof.go.jp/jgbs/reference/interest_rate/jgbcm.csv"
    },
    {
        "category": "文部科学省",
        "title": "第14回中央教育審議会生涯学習分科会社会教育の在り方に関する特別部会の配布資料を更新しました",
        "link": "https://www.mext.go.jp/b_menu/shingi/chukyo/chukyo2/015/giji_list/mext_00017.html"
    },
    {
        "category": "財務省",
        "title": "オフショア勘定残高",
        "link": "https://www.mof.go.jp/policy/international_policy/reference/offshore/data/offshore.pdf"
    },
    {
        "category": "財務省",
        "title": "対外及び対内証券売買契約等の状況(週次・指定報告機関ベース) ",
        "link": "https://www.mof.go.jp/policy/international_policy/reference/itn_transactions_in_securities/week.pdf"
    },
    {
        "category": "総務省",
        "title": "行政評価局企画課 非常勤職員採用情報",
        "link": "https://www.soumu.go.jp/menu_syokai/saiyou/detail/hyouka_260116.html"
    },
    {
        "category": "総務省",
        "title": "情報通信審議会　情報通信技術分科会　陸上無線通信委員会　5.2GHz帯及び6GHz帯無線LAN作業班（第15回）",
        "link": "https://www.soumu.go.jp/main_sosiki/joho_tsusin/policyreports/joho_tsusin/rikujou/02kiban12_04000426.html"
    },
    {
        "category": "総務省",
        "title": "行政評価局行政相談管理官室 非常勤職員採用情報",
        "link": "https://www.soumu.go.jp/menu_syokai/saiyou/detail/02hyoka02_04000068.html"
    },
    {
        "category": "厚生労働省",
        "title": "令和８年度　地域の健康増進活動支援事業について",
        "link": "https://www.mhlw.go.jp/stf/newpage_68754.html"
    },
    {
        "category": "財務省",
        "title": "製造たばこの小売定価の認可",
        "link": "https://www.mof.go.jp/policy/tab_salt/topics/kouriteika.html"
    },
    {
        "category": "厚生労働省",
        "title": "薬事工業生産動態統計令和７年10月分月報について",
        "link": "https://www.mhlw.go.jp/toukei/list/105-1c.html"
    },
    {
        "category": "農林水産省",
        "title": "食品産業の海外展開に向けた人材育成・発掘に関する情報交換会を開催！",
        "link": "https://www.maff.go.jp/j/press/yusyutu_kokusai/kaitaku/260116.html"
    },
    {
        "category": "農林水産省",
        "title": "外食産業の海外展開に関するセミナーを農林水産省で開催します！",
        "link": "https://www.maff.go.jp/j/press/yusyutu_kokusai/kaitaku/260116_1.html"
    },
    {
        "category": "財務省",
        "title": "流動性供給(第445回)入札",
        "link": "https://www.mof.go.jp/jgbs/auction/calendar/nyusatsu/offer20260116.htm"
    },
    {
        "category": "財務省",
        "title": "国庫短期証券（第1356回）の入札発行",
        "link": "https://www.mof.go.jp/jgbs/auction/calendar/tbill/tbill_nyusatsu/offer20260116.htm"
    },
    {
        "category": "文部科学省",
        "title": "教育課程部会　体育・保健体育、健康、安全ワーキンググループ（第6回）　配付資料",
        "link": "https://www.mext.go.jp/b_menu/shingi/chukyo/chukyo3/112/siryo/mext_00006.html"
    },
    {
        "category": "農林水産省",
        "title": "フードテック官民協議会ビジネスコンテスト本選大会のご案内",
        "link": "https://www.maff.go.jp/j/press/shokuhin/kikaku/260113.html"
    },
    {
        "category": "首相官邸",
        "title": "閣議の概要／内閣府の人事について",
        "link": "https://www.kantei.go.jp/jp/tyoukanpress/202601/16_a.html"
    },
    {
        "category": "国土交通省",
        "title": "「国土交通省南海トラフ巨大地震対策計画」を改定しました〜南海トラフ巨大地震に対し、省の総力を挙げて取り組む対策をとりまとめ〜",
        "link": "http://www.mlit.go.jp/report/press/mizukokudo06_hh_000339.html"
    },
    {
        "category": "国土交通省",
        "title": "令和12年度までの社会資本整備・交通政策の羅針盤となる計画を策定〜第６次「社会資本整備重点計画」・第３次「交通政策基本計画」を本日閣議決定〜",
        "link": "http://www.mlit.go.jp/report/press/sogo12_hh_000496.html"
    },
    {
        "category": "国土交通省",
        "title": "「旅行業法に基づく登録研修機関の不利益処分の基準について」を制定しました",
        "link": "http://www.mlit.go.jp/kankocho/topics06_00039.html"
    }
]