[
    {
        "category": "財務省",
        "title": "公募情報",
        "link": "https://www.mof.go.jp/application-contact/procurement/koubo/index.htm"
    },
    {
        "category": "財務省",
        "title": "研究員の募集（財務総合政策研究所）",
        "link": "https://www.mof.go.jp/about_mof/recruit/mof/jimuhosa/20260213_zaisouken_kenkyu.html"
    },
    {
        "category": "財務省",
        "title": "入札、落札結果情報（物品・役務）",
        "link": "https://www.mof.go.jp/application-contact/procurement/buppinn/index.htm"
    },
    {
        "category": "財務省",
        "title": "国債金利情報(令和8年2月12日)",
        "link": "https://www.mof.go.jp/jgbs/reference/interest_rate/jgbcm.csv"
    },
    {
        "category": "財務省",
        "title": "対外及び対内証券売買契約等の状況(週次・指定報告機関ベース) ",
        "link": "https://www.mof.go.jp/policy/international_policy/reference/itn_transactions_in_securities/week.pdf"
    },
    {
        "category": "総務省",
        "title": "情報通信審議会 電気通信事業政策部会 接続政策委員会　接続料の算定等に関するワーキンググループ（第5回）配布資料",
        "link": "https://www.soumu.go.jp/main_sosiki/joho_tsusin/policyreports/joho_tsusin/setsuzoku_seisaku/02kiban03_04001155.html"
    },
    {
        "category": "文部科学省",
        "title": "文部科学省科学技術・学術政策局政策課資源室日本食品標準成分表専門調査員（期間業務職員）採用のお知らせ（令和8年4月1日採用）",
        "link": "https://www.mext.go.jp/b_menu/saiyou/hijyoukin/1423086_00013.html"
    },
    {
        "category": "財務省",
        "title": "エネルギー対策特別会計の借入金の入札結果（令和8年2月13日入札）",
        "link": "https://www.mof.go.jp/jgbs/auction/calendar/kariire/energy-result260213.htm"
    },
    {
        "category": "財務省",
        "title": "流動性供給(第447回)入札結果",
        "link": "https://www.mof.go.jp/jgbs/auction/calendar/nyusatsu/resul20260213.htm"
    },
    {
        "category": "財務省",
        "title": "国庫短期証券（第1362回）の入札結果",
        "link": "https://www.mof.go.jp/jgbs/auction/calendar/tbill/tbill_nyusatsu/resul20260213.htm"
    },
    {
        "category": "経済産業省",
        "title": "令和7年度「わたしたちのくらしとエネルギー」かべ新聞コンテストの受賞者を決定しました",
        "link": "https://www.meti.go.jp/press/2025/02/20260213003/20260213003.html"
    },
    {
        "category": "文部科学省",
        "title": "高校教育改革に関する基本方針（グランドデザイン）",
        "link": "https://www.mext.go.jp/a_menu/shotou/kaikaku/1358056_00005.htm"
    },
    {
        "category": "経済産業省",
        "title": "松尾経済産業審議官が南アフリカ共和国に出張しました",
        "link": "https://www.meti.go.jp/press/2025/02/20260213002/20260213002.html"
    },
    {
        "category": "厚生労働省",
        "title": "薬事工業生産動態統計令和７年11月分月報について",
        "link": "https://www.mhlw.go.jp/toukei/list/105-1c.html"
    },
    {
        "category": "厚生労働省",
        "title": "採用情報（期間業務職員（大臣官房会計課）募集情報）",
        "link": "https://www.mhlw.go.jp/stf/kouseiroudoushou/saiyou/hijoukin/hj-daijinkanboukaikeika-jidousyauntengyoumu.html"
    },
    {
        "category": "経済産業省",
        "title": "赤澤経済産業大臣がラトニック米国商務長官との会談等を行いました",
        "link": "https://www.meti.go.jp/press/2025/02/20260213005/20260213005.html"
    },
    {
        "category": "農林水産省",
        "title": "令和8年度「安全な農畜水産物安定供給のための包括的レギュラトリーサイエンス研究推進委託事業（うち短期課題解決型研究）」の公募及び公募説明会の開催について",
        "link": "https://www.maff.go.jp/j/press/syouan/gijyutu/260213.html"
    },
    {
        "category": "財務省",
        "title": "流動性供給(第447回)入札",
        "link": "https://www.mof.go.jp/jgbs/auction/calendar/nyusatsu/offer20260213.htm"
    },
    {
        "category": "財務省",
        "title": "国庫短期証券（第1362回）の入札発行",
        "link": "https://www.mof.go.jp/jgbs/auction/calendar/tbill/tbill_nyusatsu/offer20260213.htm"
    },
    {
        "category": "財務省",
        "title": "国庫短期証券（第1364回）の発行予定額等",
        "link": "https://www.mof.go.jp/jgbs/auction/calendar/tbill/tbill_auct/auct20260213.htm"
    },
    {
        "category": "経済産業省",
        "title": "「DX推進指標」を改訂しました",
        "link": "https://www.meti.go.jp/press/2025/02/20260213001/20260213001.html"
    },
    {
        "category": "厚生労働省",
        "title": "適時調査実施要領を更新しました。",
        "link": "https://www.mhlw.go.jp/seisakunitsuite/bunya/kenkou_iryou/iryouhoken/shidou_kansa_jissi.html"
    },
    {
        "category": "法務省",
        "title": "令和８年司法試験に関するＱ＆Ａについて",
        "link": "http://www.moj.go.jp/jinji/shihoushiken/shiken_shinshihou_shikenqa.html"
    },
    {
        "category": "法務省",
        "title": "令和８年司法試験の受験案内について",
        "link": "http://www.moj.go.jp/jinji/shihoushiken/jinji08_00286.html"
    },
    {
        "category": "首相官邸",
        "title": "閣議の概要について",
        "link": "https://www.kantei.go.jp/jp/tyoukanpress/202602/13_a.html"
    },
    {
        "category": "内閣府",
        "title": "規制改革推進会議働き方・人への投資ワーキング・グループ（第6回）",
        "link": "https://www8.cao.go.jp/kisei-kaikaku/kisei/meeting/wg/2501_03human/260216/human06_agenda.html"
    },
    {
        "category": "国土交通省",
        "title": "日本国有鉄道清算事業団の債務等の処理に関する法律に定める施策の実施の状況に関する報告について（令和６年度）",
        "link": "http://www.mlit.go.jp/report/press/tetsudo05_hh_000160.html"
    },
    {
        "category": "警察庁",
        "title": "特殊詐欺及びSNS型投資・ロマンス詐欺の認知・検挙状況等（令和７年暫定値）について",
        "link": "http://www.npa.go.jp/newlyarrived/2026/20260209004.html"
    },
    {
        "category": "厚生労働省",
        "title": "専門実践教育訓練の指定講座を公表しました（令和８年４月１日付け指定）",
        "link": "https://www.mhlw.go.jp/stf/newpage_70323.html"
    },
    {
        "category": "厚生労働省",
        "title": "第39回キャリアコンサルタント登録制度等に関する検討会　更新講習（技能講習）作業部会の開催について",
        "link": "https://www.mhlw.go.jp/stf/newpage_69746.html"
    },
    {
        "category": "厚生労働省",
        "title": "第254回社会保障審議会介護給付費分科会（Web会議）を開催します",
        "link": "https://www.mhlw.go.jp/stf/newpage_69867.html"
    },
    {
        "category": "厚生労働省",
        "title": "特定一般教育訓練の指定講座を公表しました（令和８年４月１日付け指定）",
        "link": "https://www.mhlw.go.jp/stf/newpage_70327.html"
    },
    {
        "category": "厚生労働省",
        "title": "薬事審議会　再生医療等製品・生物由来技術部会を開催します",
        "link": "https://www.mhlw.go.jp/stf/newpage_70353.html"
    },
    {
        "category": "文部科学省",
        "title": "ヒト胚モデルの取扱いに関する関係指針の改正について",
        "link": "https://www.mext.go.jp/b_menu/houdou/mext_01604.html"
    },
    {
        "category": "文部科学省",
        "title": "ライフサイエンス委員会　感染症研究の推進に関する作業部会",
        "link": "https://www.mext.go.jp/b_menu/shingi/gijyutu/gijyutu2/117/kaisai/1419839_00001.htm"
    },
    {
        "category": "文部科学省",
        "title": "中央教育審議会初等中等教育分科会教育課程部会社会・地理歴史・公民ワーキンググループの議事録を掲載しました",
        "link": "https://www.mext.go.jp/b_menu/shingi/chukyo/chukyo3/109/gijiroku/mext_00003.html"
    },
    {
        "category": "文部科学省",
        "title": "社会教育主事・社会教育士養成等の改善・充実に関するワーキング・グループ（第4回）の開催について",
        "link": "https://www.mext.go.jp/b_menu/shingi/chukyo/chukyo2/016/kaisai/mext_00004.html"
    },
    {
        "category": "文部科学省",
        "title": "中央教育審議会初等中等教育分科会教育課程部会産業教育ワーキンググループ（第5回）を開催します",
        "link": "https://www.mext.go.jp/b_menu/shingi/chukyo/chukyo3/kaisai/mext_00106.html"
    },
    {
        "category": "文部科学省",
        "title": "中央教育審議会初等中等教育分科会体育・保健体育、健康、安全ワーキンググループ（第7回）を開催します",
        "link": "https://www.mext.go.jp/b_menu/shingi/chukyo/chukyo3/kaisai/mext_00105.html"
    },
    {
        "category": "文部科学省",
        "title": "人材委員会　科学技術人材多様化ワーキング・グループ（第7回）の開催について",
        "link": "https://www.mext.go.jp/b_menu/shingi/gijyutu/gijyutu10/007/kaisai/mext_00009.html"
    },
    {
        "category": "文部科学省",
        "title": "中央教育審議会初等中等教育分科会教育課程部会外国語ワーキンググループ（第9回）を開催します",
        "link": "https://www.mext.go.jp/b_menu/shingi/chukyo/chukyo3/108/kaisai/mext_00009.html"
    },
    {
        "category": "文部科学省",
        "title": "外国人児童生徒等の教育の充実に関する有識者会議（令和7年度）（第11回）の開催について",
        "link": "https://www.mext.go.jp/b_menu/shingi/chousa/shotou/196/kaisai/1418128_00011.html"
    },
    {
        "category": "農林水産省",
        "title": "国産麦類のかび毒の含有実態調査（令和4年度〜令和6年度）の結果について",
        "link": "https://www.maff.go.jp/j/press/syouan/nouan/260213.html"
    },
    {
        "category": "文部科学省",
        "title": "教育課程部会　情報・技術ワーキンググループ（第6回）　配付資料について",
        "link": "https://www.mext.go.jp/b_menu/shingi/chukyo/chukyo3/118/mext_00002.html"
    },
    {
        "category": "文部科学省",
        "title": "令和7年度　産業イノベーション人材育成等に資する高等学校等教育改革促進事業の公募について",
        "link": "https://www.mext.go.jp/b_menu/boshu/detail/mext_00510.html"
    },
    {
        "category": "消費者庁",
        "title": "令和7年度「めざせ!食品ロス・ゼロ」川柳コンテストアンケート結果を公表しました",
        "link": "https://www.caa.go.jp/notice/entry/045087/"
    },
    {
        "category": "法務省",
        "title": "更生保護事業者に対する天皇誕生日御下賜金の御沙汰について",
        "link": "http://www.moj.go.jp/hogo1/soumu/hogo12_00030.html"
    },
    {
        "category": "法務省",
        "title": "法制審議会第２０４回会議（令和８年２月１２日開催）",
        "link": "http://www.moj.go.jp/shingi1/shingi03500044_00013.html"
    },
    {
        "category": "経済産業省",
        "title": "松尾経済産業審議官がシンガポール共和国及びインドネシア共和国に出張しました",
        "link": "https://www.meti.go.jp/press/2025/02/20260213007/20260213007.html"
    },
    {
        "category": "消費者庁",
        "title": "令和7年度第4回食品衛生基準審議会新開発食品調査部会遺伝子組換え食品等調査会(オンライン会議:一部非公開)の開催について",
        "link": "https://www.caa.go.jp/notice/entry/045123/"
    },
    {
        "category": "財務省",
        "title": "流動性供給(第447回)入札において追加発行した国債の銘柄",
        "link": "https://www.mof.go.jp/jgbs/auction/calendar/nyusatsu/resul20260213a.htm"
    },
    {
        "category": "消費者庁",
        "title": "法人・団体向け不当寄附勧誘防止法説明会 in 仙台2026の開催(2026年3月3日)について",
        "link": "https://www.caa.go.jp/notice/entry/044996/"
    },
    {
        "category": "消費者庁",
        "title": "堀井長官記者会見要旨(2月12日)",
        "link": "https://www.caa.go.jp/notice/entry/045158/"
    },
    {
        "category": "法務省",
        "title": "司法試験等ＣＢＴプレテストのアンケートを公開しました。",
        "link": "http://www.moj.go.jp/jinji/shihoushiken/jinji08_00238.html"
    },
    {
        "category": "法務省",
        "title": "令和７年度土地家屋調査士試験の最終結果について掲載しました。",
        "link": "http://www.moj.go.jp/MINJI/minji05_00705.html"
    },
    {
        "category": "法務省",
        "title": "令和７年度土地家屋調査士試験の最終結果",
        "link": "http://www.moj.go.jp/MINJI/minji05_00746.html"
    },
    {
        "category": "法務省",
        "title": "令和７年度土地家屋調査士試験最終合格者受験番号",
        "link": "http://www.moj.go.jp/MINJI/minji05_00747.html"
    },
    {
        "category": "消費者庁",
        "title": "消費者安全法に基づく重大事故等以外の消費者事故等の事故情報データバンク登録について(2月13日)",
        "link": "https://www.caa.go.jp/notice/entry/045149/"
    },
    {
        "category": "消費者庁",
        "title": "消費者安全法の重大事故等に係る公表について(2月13日)",
        "link": "https://www.caa.go.jp/notice/entry/045150/"
    },
    {
        "category": "消費者庁",
        "title": "消費生活用製品の重大製品事故:電気洗濯機で火災等(2月13日)",
        "link": "https://www.caa.go.jp/notice/entry/045157/"
    },
    {
        "category": "内閣府",
        "title": "規制改革推進会議地域活性化・人手不足対応ワーキング・グループ（第7回）",
        "link": "https://www8.cao.go.jp/kisei-kaikaku/kisei/meeting/wg/2501_01local/260217/local07_agenda.html"
    },
    {
        "category": "文部科学省",
        "title": "教育課程部会　特別活動ワーキンググループ（第4回）の開催について",
        "link": "https://www.mext.go.jp/b_menu/shingi/chukyo/chukyo3/116/kaisai/mext_00004.html"
    },
    {
        "category": "文部科学省",
        "title": "松本洋平文部科学大臣記者会見録（令和8年2月13日）",
        "link": "https://www.mext.go.jp/b_menu/daijin/detail/mext_00666.html"
    },
    {
        "category": "財務省",
        "title": "片山財務大臣兼内閣府特命担当大臣閣議後記者会見の概要(令和8年2月13日(金曜日))",
        "link": "https://www.mof.go.jp/public_relations/conference/my20260213.html"
    },
    {
        "category": "厚生労働省",
        "title": "令和７年度第５回医薬品等安全対策部会安全対策調査会 議事録",
        "link": "https://www.mhlw.go.jp/stf/newpage_70465.html"
    },
    {
        "category": "防衛省",
        "title": "戦術ＡＩ衛星の実証の進捗状況について",
        "link": "https://www.mod.go.jp/j/press/news/2026/02/13b.html"
    },
    {
        "category": "防衛省",
        "title": "防衛省について｜吉田防衛大臣政務官の動静（横田基地視察）を更新",
        "link": "https://www.mod.go.jp/j/profile/minister/vice-minister/yoshida.html#photo_20260212a"
    },
    {
        "category": "防衛省",
        "title": "防衛省について｜防衛省ヘリポートの使用予定について（2月11日現在）を更新",
        "link": "https://www.mod.go.jp/j/profile/chouwa/heliport/index.html"
    },
    {
        "category": "防衛省",
        "title": "予算・調達｜入札参加資格（競争参加資格の申請・変更について、令和７・８年度有資格者名簿（令和８年２月１３日更新））を更新",
        "link": "https://www.mod.go.jp/j/budget/shikaku/index.html"
    },
    {
        "category": "防衛省",
        "title": "防衛省の取組｜能力構築支援（モンゴル　PKO（施設））を掲載",
        "link": "https://www.mod.go.jp/j/approach/exchange/cap_build/2025/20250519_mng.html"
    },
    {
        "category": "防衛省",
        "title": "防衛省について｜吉田防衛大臣政務官の動静（企業視察）を更新",
        "link": "https://www.mod.go.jp/j/profile/minister/vice-minister/yoshida.html#photo_20260210a"
    },
    {
        "category": "防衛省",
        "title": "予算・調達｜内部部局（2月13日付:一般競争入札（政府調達以外））を更新",
        "link": "https://www.mod.go.jp/j/budget/chotatsu/naikyoku/nyuusatu/index.html"
    },
    {
        "category": "厚生労働省",
        "title": "薬事工業生産動態統計の更新について",
        "link": "https://www.mhlw.go.jp/toukei/list/105-1.html"
    },
    {
        "category": "文部科学省",
        "title": "高等学校教育改革促進基金",
        "link": "https://www.mext.go.jp/a_menu/shotou/kaikaku/1358056_00006.htm"
    },
    {
        "category": "文部科学省",
        "title": "教育課程部会　算数・数学ワーキンググループ（第6回）　配付資料",
        "link": "https://www.mext.go.jp/b_menu/shingi/chukyo/chukyo3/110/siryo/mext_00005.html"
    },
    {
        "category": "厚生労働省",
        "title": "令和８年度高齢者医療運営円滑化等補助金における健康保険組合による保健事業（PFS事業）の公募について",
        "link": "https://www.mhlw.go.jp/stf/seisakunitsuite/bunya/kenkou_iryou/iryouhoken/dh-kenpo_hojokin2026.html"
    }
]